oidc_provider_mock/__init__.py
oidc_provider_mock/__main__.py
oidc_provider_mock/_app.py
oidc_provider_mock/_client.py
oidc_provider_mock/_client_lib.py
oidc_provider_mock/_server.py
oidc_provider_mock/_storage.py
oidc_provider_mock/templates/_base.html
oidc_provider_mock/templates/authorization_form.html
oidc_provider_mock/templates/end_session_confirm.html
oidc_provider_mock/templates/end_session_form.html
oidc_provider_mock/templates/error.html
oidc_provider_mock/templates/index.html
oidc_provider_mock-0.3.4.dist-info/METADATA
oidc_provider_mock-0.3.4.dist-info/WHEEL
oidc_provider_mock-0.3.4.dist-info/entry_points.txt
oidc_provider_mock-0.3.4.dist-info/licenses/LICENSE.txt
oidc_provider_mock-0.3.4.dist-info/RECORD
