Metadata-Version: 2.4
Name: oidc-provider-mock
Version: 0.3.4
Summary: OpenID Connect provider server for testing authentication
Project-URL: Homepage, https://github.com/geigerzaehler/oidc-provider-mock
Project-URL: Documentation, https://github.com/geigerzaehler/oidc-provider-mock
Project-URL: Source, https://github.com/geigerzaehler/oidc-provider-mock
Project-URL: Issues, https://github.com/geigerzaehler/oidc-provider-mock/issues
Author-email: Thomas Scholtes <geigerzaehler@axiom.fm>
License-Expression: MIT
License-File: LICENSE.txt
Keywords: OAuth,OIDC,OpenID Connect,authentication,development,mock,testing
Classifier: Development Status :: 4 - Beta
Classifier: Intended Audience :: Developers
Classifier: License :: OSI Approved :: MIT License
Classifier: Programming Language :: Python
Classifier: Programming Language :: Python :: 3
Classifier: Programming Language :: Python :: 3.8
Classifier: Programming Language :: Python :: 3.9
Classifier: Programming Language :: Python :: 3.10
Classifier: Programming Language :: Python :: 3.11
Classifier: Topic :: Internet :: WWW/HTTP :: HTTP Servers
Classifier: Topic :: Security
Classifier: Topic :: Software Development :: Testing
Classifier: Topic :: Software Development :: Testing :: Mocking
Requires-Python: >=3.10
Requires-Dist: authlib>=1.5
Requires-Dist: flask>=3.1
Requires-Dist: htpy>=25.2.0
Requires-Dist: httpx>=0.26
Requires-Dist: joserfc>=1.0.3
Requires-Dist: pydantic>=2.0
Requires-Dist: typing-extensions>=4.0
Requires-Dist: uvicorn>=0.30.0
